scrapy_mongoengine_item/__init__.py
scrapy_mongoengine_item-0.1.5.dist-info/LICENSE_GPL2.0.txt
scrapy_mongoengine_item-0.1.5.dist-info/LICENSE_LGPL_2.1.txt
scrapy_mongoengine_item-0.1.5.dist-info/METADATA
scrapy_mongoengine_item-0.1.5.dist-info/WHEEL
scrapy_mongoengine_item-0.1.5.dist-info/top_level.txt
scrapy_mongoengine_item-0.1.5.dist-info/RECORD
